<annotation>
	<folder>Backup</folder>
	<filename>img_CAMERA1_1261233830.315790_left.jpg</filename>
	<path>D:\Facultate\Anul4\Licenta\Cod\ModelDetectie\Dataset\Backup\img_CAMERA1_1261233830.315790_left.jpg</path>
	<source>
		<database>Unknown</database>
	</source>
	<size>
		<width>800</width>
		<height>600</height>
		<depth>3</depth>
	</size>
	<segmented>0</segmented>
	<object>
		<name>STRAIGHT</name>
		<pose>Unspecified</pose>
		<truncated>0</truncated>
		<difficult>0</difficult>
		<bndbox>
			<xmin>407</xmin>
			<ymin>466</ymin>
			<xmax>457</xmax>
			<ymax>530</ymax>
		</bndbox>
	</object>
	<object>
		<name>STRAIGHT</name>
		<pose>Unspecified</pose>
		<truncated>0</truncated>
		<difficult>0</difficult>
		<bndbox>
			<xmin>192</xmin>
			<ymin>462</ymin>
			<xmax>294</xmax>
			<ymax>524</ymax>
		</bndbox>
	</object>
</annotation>
