<annotation>
	<folder>Backup</folder>
	<filename>img_CAMERA1_1261232728.805581_left.jpg</filename>
	<path>D:\Facultate\Anul4\Licenta\Cod\ModelDetectie\Dataset\Backup\img_CAMERA1_1261232728.805581_left.jpg</path>
	<source>
		<database>Unknown</database>
	</source>
	<size>
		<width>800</width>
		<height>600</height>
		<depth>3</depth>
	</size>
	<segmented>0</segmented>
	<object>
		<name>STRAIGHT</name>
		<pose>Unspecified</pose>
		<truncated>1</truncated>
		<difficult>0</difficult>
		<bndbox>
			<xmin>345</xmin>
			<ymin>487</ymin>
			<xmax>420</xmax>
			<ymax>600</ymax>
		</bndbox>
	</object>
	<object>
		<name>STRAIGHT</name>
		<pose>Unspecified</pose>
		<truncated>1</truncated>
		<difficult>0</difficult>
		<bndbox>
			<xmin>601</xmin>
			<ymin>488</ymin>
			<xmax>799</xmax>
			<ymax>600</ymax>
		</bndbox>
	</object>
	<object>
		<name>STRAIGHT</name>
		<pose>Unspecified</pose>
		<truncated>1</truncated>
		<difficult>0</difficult>
		<bndbox>
			<xmin>1</xmin>
			<ymin>490</ymin>
			<xmax>185</xmax>
			<ymax>593</ymax>
		</bndbox>
	</object>
	<object>
		<name>STRAIGHT</name>
		<pose>Unspecified</pose>
		<truncated>0</truncated>
		<difficult>0</difficult>
		<bndbox>
			<xmin>388</xmin>
			<ymin>406</ymin>
			<xmax>409</xmax>
			<ymax>415</ymax>
		</bndbox>
	</object>
	<object>
		<name>STRAIGHT</name>
		<pose>Unspecified</pose>
		<truncated>0</truncated>
		<difficult>0</difficult>
		<bndbox>
			<xmin>334</xmin>
			<ymin>407</ymin>
			<xmax>350</xmax>
			<ymax>416</ymax>
		</bndbox>
	</object>
</annotation>
